Workbook

Sheet Tasks
A1: ID | B1: Phase | C1: Task | D1: Subtask | E1: Details / Description | F1: Priority | G1: Est. Hours | H1: Status | I1: Dependencies
A2: T-001 | B2: 1. Project Setup & Environment | C2: Initialize Tauri + React project | D2: Scaffold project with Tauri CLI | E2: Run `create-tauri-app` with React + Vite template; verify native window launches on Windows. | F2: High | G2: 3 | H2: Completed
A3: T-002 | B3: 1. Project Setup & Environment | C3: Initialize Tauri + React project | D3: Configure Tailwind CSS | E3: Install Tailwind, set up config and base styles, confirm hot-reload works inside the Tauri window. | F3: High | G3: 2 | H3: Completed
A4: T-003 | B4: 1. Project Setup & Environment | C4: Initialize Tauri + React project | D4: Set up project folder structure | E4: Create feature-based folder structure: /features (orders, menu, payments), /components, /lib, /store. | F4: Medium | G4: 2 | H4: Completed
A5: T-004 | B5: 1. Project Setup & Environment | C5: Version control & tooling | D5: Set up Git repository and branching strategy | E5: Initialize repo, set up main/dev branches, add .gitignore for Tauri/Rust/Node artifacts. | F5: Medium | G5: 1 | H5: Completed
A6: T-005 | B6: 1. Project Setup & Environment | C6: Version control & tooling | D6: Configure ESLint, Prettier, and commit hooks | E6: Add lint/format config consistent with existing MERN projects; add pre-commit hook via husky. | F6: Low | G6: 2 | H6: Completed
A7: T-006 | B7: 1. Project Setup & Environment | C7: Backend project setup | D7: Initialize Node.js + Express project | E7: Scaffold Express app with folder structure for routes/controllers/services/models. | F7: High | G7: 2 | H7: Completed
A8: T-007 | B8: 1. Project Setup & Environment | C8: Backend project setup | D8: Set up PostgreSQL and Prisma | E8: Install PostgreSQL locally, configure Prisma, run first migration to confirm connectivity. | F8: High | G8: 3 | H8: Completed
A9: T-008 | B9: 1. Project Setup & Environment | C9: Local database setup | D9: Integrate SQLite via tauri-plugin-sql | E9: Add SQLite plugin to Tauri app, confirm read/write from React front end through Rust bridge. | F9: High | G9: 3 | H9: Completed
A10: T-009 | B10: 2. Database & Schema Design | C10: Design local SQLite schema | D10: Define core tables (orders, order_items, payments) | E10: Design tables mirroring SRS data model with UUID primary keys, synced/created_locally_at fields. | F10: High | G10: 5 | H10: Not Started
A11: T-010 | B11: 2. Database & Schema Design | C11: Design local SQLite schema | D11: Define menu & inventory tables | E11: menu_categories, menu_items, item_variants, modifiers, ingredients, recipe_links tables. | F11: High | G11: 4 | H11: Not Started
A12: T-011 | B12: 2. Database & Schema Design | C12: Design local SQLite schema | D12: Define users & audit tables | E12: users, roles, audit_log tables with hashed PIN storage. | F12: High | G12: 2 | H12: Not Started
A13: T-012 | B13: 2. Database & Schema Design | C13: Design backend PostgreSQL schema | D13: Mirror local schema on server with sync metadata | E13: Add synced_at, server_received_at, conflict_flag columns for reconciliation logic. | F13: High | G13: 4 | H13: Not Started
... A82: T-081 | B82: 14. Deployment & Packaging | C82: Go-live | D82: Post-launch monitoring and hotfix window | E82: Monitor first week of live usage for sync issues, printer errors, and bugs. | F82: Medium | G82: 4 | H82: Not Started

Sheet Summary
A1: Phase | B1: Task Count | C1: Total Est. Hours
A2: 1. Project Setup & Environment | B2: =COUNTIF(Tasks!$B$2:$B$82,A2) -> 8 | C2: =SUMIF(Tasks!$B$2:$B$82,A2,Tasks!$G$2:$G$82) -> 18
A3: 2. Database & Schema Design | B3: =COUNTIF(Tasks!$B$2:$B$82,A3) -> 6 | C3: =SUMIF(Tasks!$B$2:$B$82,A3,Tasks!$G$2:$G$82) -> 20
A4: 3. Authentication & User Management | B4: =COUNTIF(Tasks!$B$2:$B$82,A4) -> 7 | C4: =SUMIF(Tasks!$B$2:$B$82,A4,Tasks!$G$2:$G$82) -> 23
A5: 4. Menu Management | B5: =COUNTIF(Tasks!$B$2:$B$82,A5) -> 7 | C5: =SUMIF(Tasks!$B$2:$B$82,A5,Tasks!$G$2:$G$82) -> 26
A6: 5. Order Management | B6: =COUNTIF(Tasks!$B$2:$B$82,A6) -> 8 | C6: =SUMIF(Tasks!$B$2:$B$82,A6,Tasks!$G$2:$G$82) -> 29
A7: 6. Table & Floor Management | B7: =COUNTIF(Tasks!$B$2:$B$82,A7) -> 4 | C7: =SUMIF(Tasks!$B$2:$B$82,A7,Tasks!$G$2:$G$82) -> 14
A8: 7. Kitchen Display System (KDS) | B8: =COUNTIF(Tasks!$B$2:$B$82,A8) -> 5 | C8: =SUMIF(Tasks!$B$2:$B$82,A8,Tasks!$G$2:$G$82) -> 17
A9: 8. Payment Processing | B9: =COUNTIF(Tasks!$B$2:$B$82,A9) -> 6 | C9: =SUMIF(Tasks!$B$2:$B$82,A9,Tasks!$G$2:$G$82) -> 20
A10: 9. Inventory Management | B10: =COUNTIF(Tasks!$B$2:$B$82,A10) -> 5 | C10: =SUMIF(Tasks!$B$2:$B$82,A10,Tasks!$G$2:$G$82) -> 15
A11: 10. Receipt & Printing | B11: =COUNTIF(Tasks!$B$2:$B$82,A11) -> 5 | C11: =SUMIF(Tasks!$B$2:$B$82,A11,Tasks!$G$2:$G$82) -> 16
A12: 11. Offline Operation & Sync Engine | B12: =COUNTIF(Tasks!$B$2:$B$82,A12) -> 5 | C12: =SUMIF(Tasks!$B$2:$B$82,A12,Tasks!$G$2:$G$82) -> 19
A13: 12. Reporting & Analytics | B13: =COUNTIF(Tasks!$B$2:$B$82,A13) -> 5 | C13: =SUMIF(Tasks!$B$2:$B$82,A13,Tasks!$G$2:$G$82) -> 15
... A15: 14. Deployment & Packaging | B15: =COUNTIF(Tasks!$B$2:$B$82,A15) -> 5 | C15: =SUMIF(Tasks!$B$2:$B$82,A15,Tasks!$G$2:$G$82) -> 17
A16: TOTAL | B16: =SUM(B2:B15) -> 81 | C16: =SUM(C2:C15) -> 269
